minotaur_trading/__init__.py
minotaur_trading/models/__init__.py
minotaur_trading/notebooks/__init__.py
minotaur_trading/notebooks/examples.py
minotaur_trading/src/__init__.py
minotaur_trading/src/simple_chart.py
minotaur_trading-1.7.4.data/scripts/minotaur-trading
notebooks/__init__.py
notebooks/examples.py
src/__init__.py
src/simple_chart.py
minotaur_trading-1.7.4.dist-info/LICENSE
minotaur_trading-1.7.4.dist-info/METADATA
minotaur_trading-1.7.4.dist-info/WHEEL
minotaur_trading-1.7.4.dist-info/top_level.txt
minotaur_trading-1.7.4.dist-info/RECORD
