Metadata-Version: 2.1
Name: minotaur-trading
Version: 1.7.4
Summary: Machine learning tool for trading built for non-data scientist to easily applying data science concept into trading knowledge
Home-page: https://github.com/Anggi-Permana-Harianja/minotaur-trading
Author: Anggi Permana Harianja
Author-email: permanaharianja@gmail.com
License: UNKNOWN
Platform: UNKNOWN
Classifier: Programming Language :: Python :: 3
Classifier: License :: OSI Approved :: GNU General Public License v3 (GPLv3)
Classifier: Operating System :: OS Independent
